damv1mps2301k8salert/__init__.py
damv1mps2301k8salert/production_mymps2301k8salert.py
damv1mps2301k8salert/sandbox_mymps2301k8salert.py
damv1mps2301k8salert-0.2.10.dist-info/METADATA
damv1mps2301k8salert-0.2.10.dist-info/WHEEL
damv1mps2301k8salert-0.2.10.dist-info/top_level.txt
damv1mps2301k8salert-0.2.10.dist-info/RECORD
