Metadata-Version: 2.1
Name: damv1mps2301k8salert
Version: 0.2.10
Summary: damv1mps2301k8salert package
Home-page: UNKNOWN
Author: dhonyabumuhammad (Bekasi)
Author-email: <dhony.priniardi.m@gmail.com>
License: UNKNOWN
Keywords: damv1mps2301k8salert
Platform: UNKNOWN
Classifier: Development Status :: 1 - Planning
Classifier: Intended Audience :: Developers
Classifier: Programming Language :: Python :: 3
Classifier: Operating System :: Unix
Classifier: Operating System :: MacOS :: MacOS X
Classifier: Operating System :: Microsoft :: Windows
Requires-Dist: damv1time7
Requires-Dist: damv1airtableprojectk8salert
Requires-Dist: damv1xsandboxk8salertreleasev2
Requires-Dist: stringcase
